nonebot_plugin_record/__init__.py
nonebot_plugin_record/baidu.py
nonebot_plugin_record/config.py
nonebot_plugin_record/tencent.py
nonebot_plugin_record-1.0.5.dist-info/LICENSE
nonebot_plugin_record-1.0.5.dist-info/METADATA
nonebot_plugin_record-1.0.5.dist-info/WHEEL
nonebot_plugin_record-1.0.5.dist-info/RECORD
