Metadata-Version: 2.1
Name: nonebot-plugin-record
Version: 1.0.5
Summary: 基于 Nonebot2 的语音功能适配插件，包括语音事件响应器，语音识别、语音合成等功能
Home-page: https://github.com/itsevin/nonebot_plugin_record
License: MIT
Keywords: nonebot,nonebot2,nonebot_plugin_record
Author: ITSevin
Author-email: itsevin@qq.com
Requires-Python: >=3.8,<4.0
Classifier: License :: OSI Approved :: MIT License
Classifier: Programming Language :: Python :: 3
Classifier: Programming Language :: Python :: 3.8
Classifier: Programming Language :: Python :: 3.9
Classifier: Programming Language :: Python :: 3.10
Classifier: Programming Language :: Python :: 3.11
Requires-Dist: httpx (>=0.23.3,<0.24.0)
Requires-Dist: nonebot-adapter-onebot (>=2.0.0-beta.1,<3.0.0)
Requires-Dist: nonebot2 (>=2.0.0-beta.1,<3.0.0)
Requires-Dist: pilk (>=0.2.3,<0.3.0)
Project-URL: Documentation, https://github.com/itsevin/nonebot_plugin_record#readme
Project-URL: Repository, https://github.com/itsevin/nonebot_plugin_record
